README.txt
setup.cfg
setup.py
examples/basic/README.txt
examples/basic/setup.py
examples/basic/akimbo/__init__.py
examples/custom_directives/README.txt
examples/custom_directives/setup.py
examples/custom_directives/foozilate/__init__.py
examples/custom_directives/foozilate/directives.py
wikir/__init__.py
wikir/commands.py
wikir/wikir.py
wikir.egg-info/PKG-INFO
wikir.egg-info/SOURCES.txt
wikir.egg-info/dependency_links.txt
wikir.egg-info/entry_points.txt
wikir.egg-info/requires.txt
wikir.egg-info/top_level.txt
wikir/tests/__init__.py
wikir/tests/shelldoc.py
wikir/tests/test_docs.py
wikir/tests/test_shelldoc.py
wikir/tests/test_syntax.py