Metadata-Version: 1.0
Name: wikir
Version: 0.4
Summary: Publish RST documents in Wiki format.
Home-page: http://code.google.com/p/wikir/
Author: Kumar McMillan
Author-email: kumar.mcmillan@gmail.com
License: MIT License
Platform: UNKNOWN
